{
  "title": "OMNIA-MINIMAL: Structural Evaluation over Admissible Transformations",
  "upload_type": "software",
  "description": "OMNIA-MINIMAL defines a minimal technical threshold for structural evaluation over admissible transformations: single-form correctness is not structural stability. This release adds an explicit alignment between OMNIA-MINIMAL and metamorphic testing, including the expected compatibility relation R and the violation-rate specialization.",
  "creators": [
    {
      "name": "Brighindi, Massimiliano",
      "affiliation": "Independent researcher"
    }
  ],
  "access_right": "open",
  "keywords": [
    "OMNIA",
    "OMNIABASE",
    "structural observability",
    "stability",
    "fragility",
    "admissible transformations",
    "AI evaluation",
    "dispersion",
    "structural evaluation",
    "metamorphic testing",
    "metamorphic relation"
  ],
  "related_identifiers": [
    {
      "identifier": "https://github.com/Tuttotorna/OMNIA-MINIMAL",
      "relation": "isSupplementTo",
      "scheme": "url"
    }
  ]
}
